{
    "openapi": "3.0.2",
    "info": {
        "title": "Sample Api",
        "version": "3.0.2"
    },
    "paths": {
        "/api_path": {
            "get": {
                "description": "",
                "summary": "",
                "operationId": "[get]_/api_path",
                "responses": {
                    "200": {
                        "description": "Response description",
                        "content": {
                            "application/json": {
                                "schema": {
                                    "$ref": "#/components/schemas/DataclassObject"
                                }
                            }
                        }
                    }
                },
                "parameters": [
                    {
                        "required": true,
                        "name": "param_name",
                        "in": "query",
                        "schema": {
                            "type": "string",
                            "title": "Param_Name"
                        }
                    }
                ]
            }
        }
    },
    "components": {
        "schemas": {
            "DataclassObject": {
                "title": "DataclassObject",
                "required": [
                    "str_field",
                    "int_field",
                    "float_field",
                    "boolean_field",
                    "list_field"
                ],
                "type": "object",
                "properties": {
                    "str_field": {
                        "type": "string"
                    },
                    "int_field": {
                        "type": "integer"
                    },
                    "float_field": {
                        "type": "number"
                    },
                    "boolean_field": {
                        "type": "boolean"
                    },
                    "list_field": {
                        "type": "array",
                        "items": {
                            "type": "string"
                        }
                    }
                }
            }
        }
    }
}